odoo/addons/shopinvader_sale_amount_by_group/README.rst
odoo/addons/shopinvader_sale_amount_by_group/__init__.py
odoo/addons/shopinvader_sale_amount_by_group/__manifest__.py
odoo/addons/shopinvader_sale_amount_by_group/demo/account.xml
odoo/addons/shopinvader_sale_amount_by_group/i18n/shopinvader_sale_amount_by_group.pot
odoo/addons/shopinvader_sale_amount_by_group/readme/CONTRIBUTORS.rst
odoo/addons/shopinvader_sale_amount_by_group/readme/DESCRIPTION.rst
odoo/addons/shopinvader_sale_amount_by_group/services/__init__.py
odoo/addons/shopinvader_sale_amount_by_group/services/abstract_sale.py
odoo/addons/shopinvader_sale_amount_by_group/static/description/index.html
odoo/addons/shopinvader_sale_amount_by_group/tests/__init__.py
odoo/addons/shopinvader_sale_amount_by_group/tests/test_cart.py
odoo14_addon_shopinvader_sale_amount_by_group-14.0.1.0.1.dev3.dist-info/METADATA
odoo14_addon_shopinvader_sale_amount_by_group-14.0.1.0.1.dev3.dist-info/WHEEL
odoo14_addon_shopinvader_sale_amount_by_group-14.0.1.0.1.dev3.dist-info/top_level.txt
odoo14_addon_shopinvader_sale_amount_by_group-14.0.1.0.1.dev3.dist-info/RECORD
